{
    "dias": [
        "Lunes","Martes","Miércoles","Jueves","Viernes"
    ],
    "modulos": [
        1,2,3,4,5,6,7,8,9
    ],
    "ramos_con_modulos_seguidos": [
        "Educación_Física", "Artes_Visuales"
    ],
    "combinaciones": [
        [1,2],
        [2,3],
        [4,5],
        [6,7],
        [8,9]
    ],
    "horarios": {
        "1A": {
            "Lunes": [1,2,3,4,5,6,7],
            "Martes": [1,2,3,4,5,6,7,8],
            "Miércoles": [1,2,3,4,5,6,7,8],
            "Jueves": [1,2,3,4,5,6,7,8], 
            "Viernes": [1,2,3,4,5,6,7]
        },
        "1B": {
            "Lunes": [1,2,3,4,5,6,7],
            "Martes": [1,2,3,4,5,6,7,8],
            "Miércoles": [1,2,3,4,5,6,7,8],
            "Jueves": [1,2,3,4,5,6,7,8], 
            "Viernes": [1,2,3,4,5,6,7]
        },
        "2A": {
            "Lunes": [1,2,3,4,5,6,7],
            "Martes": [1,2,3,4,5,6,7,8],
            "Miércoles": [1,2,3,4,5,6,7,8],
            "Jueves": [1,2,3,4,5,6,7,8], 
            "Viernes": [1,2,3,4,5,6,7]
        },
        "2B": {
            "Lunes": [1,2,3,4,5,6,7],
            "Martes": [1,2,3,4,5,6,7,8],
            "Miércoles": [1,2,3,4,5,6,7,8],
            "Jueves": [1,2,3,4,5,6,7,8], 
            "Viernes": [1,2,3,4,5,6,7]
        }
    },
    "carga_profesores": {
        "Pérez": {
            "1": [
                ["1A", "Matemáticas"],
                ["1A", "Artes_Visuales"],
                ["2A", "Matemáticas"],
                ["2A", "Artes_Visuales"]
            ]
        },
        "Rodríguez": {
            "1": [
                ["1A", "Lenguaje"],
                ["1A", "Historia"],
                ["1A", "Ciencias_Naturales"],
                ["2A", "Lenguaje"],
                ["2A", "Historia"],
                ["2A", "Ciencias_Naturales"]
            ]
        },
        "González": {
            "1": [
                ["1A", "Música"],
                ["1A", "Educación_Física"],
                ["1A", "Orientación"],
                ["1A", "Tecnología"],
                ["1A", "Religión"],
                ["2A", "Música"],
                ["2B", "Música"],
                ["2A", "Educación_Física"],
                ["2A", "Tecnología"],
                ["2A", "Religión"]
            ],
            "2": [
                ["2A", "Educación_Física"],
                ["2B", "Educación_Física"]
            ]
        },
        "Messi": {
            "1": [
                ["1B", "Lenguaje"],
                ["1B", "Matemáticas"],
                ["1B", "Historia"]
            ]
        },
        "Mbappé": {
            "1": [
                ["1B", "Artes_Visuales"],
                ["1B", "Educación_Física"],
                ["1B", "Orientación"],
                ["1B", "Tecnología"],
                ["2B", "Tecnología"]
            ],
            "2": [ 
                ["2A", "Educación_Física"],
                ["2B", "Educación_Física"],
                ["2A", "Orientación"],
                ["2B", "Orientación"]
            ]
        },
        "Ronaldo": {
            "1": [
                ["1B", "Música"],
                ["1B", "Religión"],
                ["1B", "Ciencias_Naturales"]
            ]
        },
        "Hakimi": {
            "1": [
                ["2B", "Lenguaje"],
                ["2A", "Música"],
                ["2B", "Música"],
                ["2B", "Religión"],
                ["2B", "Ciencias_Naturales"]
            ]
        },
        "Maradona": {
            "1": [
                ["2B", "Matemáticas"],
                ["2B", "Artes_Visuales"],
                ["2B", "Historia"]
            ]
        }
    },
    "profesores_por_curso": {
        "1A": {
            "1": [
                ["Rodríguez", "Lenguaje"],
                ["Pérez", "Matemáticas"],
                ["Rodríguez", "Historia"],
                ["Pérez", "Artes_Visuales"],
                ["González", "Música"],
                ["González", "Educación_Física"],
                ["González", "Orientación"],
                ["González", "Tecnología"],
                ["González", "Religión"],
                ["Rodríguez", "Ciencias_Naturales"]
            ]
        },
        "1B": {
            "1": [
                ["Messi", "Lenguaje"],
                ["Messi", "Matemáticas"],
                ["Messi", "Historia"],
                ["Mbappé", "Artes_Visuales"],
                ["Ronaldo", "Música"],
                ["Mbappé", "Educación_Física"],
                ["Mbappé", "Orientación"],
                ["Mbappé", "Tecnología"],
                ["Ronaldo", "Religión"],
                ["Ronaldo", "Ciencias_Naturales"]
            ]
        },
        "2A": {
            "1": [
                ["Rodríguez", "Lenguaje"],
                ["Pérez", "Matemáticas"],
                ["Rodríguez", "Historia"],
                ["Pérez", "Artes_Visuales"],
                ["Mbappé", "Orientación"],
                ["González", "Tecnología"],
                ["González", "Religión"],
                ["Rodríguez", "Ciencias_Naturales"]
            ],
            "M": [
                ["González", "Educación_Física"],
                ["Mbappé", "Educación_Física"],
                ["González", "Música"],
                ["Hakimi", "Música"]
            ]
        },
        "2B": {
            "1": [
                ["Hakimi", "Lenguaje"],
                ["Maradona", "Matemáticas"],
                ["Maradona", "Historia"],
                ["Maradona", "Artes_Visuales"],
                ["Mbappé", "Orientación"],
                ["Mbappé", "Tecnología"],
                ["Hakimi", "Religión"],
                ["Hakimi", "Ciencias_Naturales"]
            ],
            "M": [
                ["González", "Educación_Física"],
                ["Mbappé", "Educación_Física"],
                ["González", "Música"],
                ["Hakimi", "Música"]
            ]
        }        
    },
    "multiples_cursos": [
        [["2A", "2B"], "Mbappé", "Orientación"],
        [["2A", "2B"], "González", "Educación_Física"],
        [["2A", "2B"], "Mbappé", "Educación_Física"]
    ],
    "multiples_profesores": [
        ["2A", ["González", "Hakimi"], "Música"],
        ["2B", ["González", "Hakimi"], "Música"],
        ["2A", ["González", "Mbappé"], "Educación_Física"],
        ["2B", ["González", "Mbappé"], "Educación_Física"]
    ],
    "ramos_por_curso": {
        "1A": {
            "Lenguaje": 8,
            "Matemáticas": 7,
            "Historia": 3,
            "Artes_Visuales": 3,
            "Música": 3,
            "Educación_Física": 4,
            "Orientación": 2,
            "Tecnología": 2,
            "Religión": 2,
            "Ciencias_Naturales": 4
        },
        "1B": {
            "Lenguaje": 8,
            "Matemáticas": 7,
            "Historia": 3,
            "Artes_Visuales": 3,
            "Música": 3,
            "Educación_Física": 4,
            "Orientación": 2,
            "Tecnología": 2,
            "Religión": 2,
            "Ciencias_Naturales": 4
        },
        "2A": {
            "Lenguaje": 8,
            "Matemáticas": 7,
            "Historia": 3,
            "Artes_Visuales": 3,
            "Música": 3,
            "Educación_Física": 4,
            "Orientación": 2,
            "Tecnología": 2,
            "Religión": 2,
            "Ciencias_Naturales": 4
        },
        "2B": {
            "Lenguaje": 8,
            "Matemáticas": 7,
            "Historia": 3,
            "Artes_Visuales": 3,
            "Música": 3,
            "Educación_Física": 4,
            "Orientación": 2,
            "Tecnología": 2,
            "Religión": 2,
            "Ciencias_Naturales": 4
        }
    }
}